vtb_http_interaction/__init__.py
vtb_http_interaction/errors.py
vtb_http_interaction/http_utils.py
vtb_http_interaction/keycloak_gateway.py
vtb_http_interaction/process_authorization_header.py
vtb_http_interaction/services.py
vtb_http_interaction-0.1.7.dist-info/METADATA
vtb_http_interaction-0.1.7.dist-info/WHEEL
vtb_http_interaction-0.1.7.dist-info/top_level.txt
vtb_http_interaction-0.1.7.dist-info/RECORD
