Metadata-Version: 2.1
Name: vtb-http-interaction
Version: 0.1.7
Summary: Межсервисное взаимодействие на основе протокола HTTP
Author: VTB python team
Author-email: python.team@vtb.ru
License: UNKNOWN
Keywords: python,microservices,utils,http
Platform: UNKNOWN
Classifier: Programming Language :: Python :: 3.8
Classifier: Operating System :: OS Independent
Requires-Python: >=3.8
Requires-Dist: aiohttp (~=3.7)
Requires-Dist: python-keycloak (==0.24)
Requires-Dist: aioredis (>=1.3)
Requires-Dist: vtb-py-logging (>=1.1.6)
Provides-Extra: test
Requires-Dist: pytest ; extra == 'test'
Requires-Dist: pytest-cov ; extra == 'test'
Requires-Dist: pytest-aiohttp ; extra == 'test'
Requires-Dist: pytest-mock ; extra == 'test'
Requires-Dist: pylint ; extra == 'test'
Requires-Dist: pytest-dotenv ; extra == 'test'
Requires-Dist: envparse ; extra == 'test'
Requires-Dist: asynctest ; extra == 'test'
